pybotx/__init__.py
pybotx/async_buffer.py
pybotx/bot/__init__.py
pybotx/bot/api/__init__.py
pybotx/bot/api/exceptions.py
pybotx/bot/api/responses/__init__.py
pybotx/bot/api/responses/bot_disabled.py
pybotx/bot/api/responses/command_accepted.py
pybotx/bot/api/responses/unverified_request.py
pybotx/bot/bot.py
pybotx/bot/bot_accounts_storage.py
pybotx/bot/callbacks/__init__.py
pybotx/bot/callbacks/callback_manager.py
pybotx/bot/callbacks/callback_memory_repo.py
pybotx/bot/callbacks/callback_repo_proto.py
pybotx/bot/contextvars.py
pybotx/bot/exceptions.py
pybotx/bot/handler.py
pybotx/bot/handler_collector.py
pybotx/bot/middlewares/__init__.py
pybotx/bot/middlewares/exception_middleware.py
pybotx/bot/testing.py
pybotx/client/__init__.py
pybotx/client/authorized_botx_method.py
pybotx/client/bots_api/__init__.py
pybotx/client/bots_api/bot_catalog.py
pybotx/client/bots_api/get_token.py
pybotx/client/botx_method.py
pybotx/client/chats_api/__init__.py
pybotx/client/chats_api/add_admin.py
pybotx/client/chats_api/add_user.py
pybotx/client/chats_api/chat_info.py
pybotx/client/chats_api/create_chat.py
pybotx/client/chats_api/create_thread.py
pybotx/client/chats_api/disable_stealth.py
pybotx/client/chats_api/list_chats.py
pybotx/client/chats_api/pin_message.py
pybotx/client/chats_api/remove_user.py
pybotx/client/chats_api/set_stealth.py
pybotx/client/chats_api/unpin_message.py
pybotx/client/events_api/__init__.py
pybotx/client/events_api/delete_event.py
pybotx/client/events_api/edit_event.py
pybotx/client/events_api/message_status_event.py
pybotx/client/events_api/reply_event.py
pybotx/client/events_api/stop_typing_event.py
pybotx/client/events_api/typing_event.py
pybotx/client/exceptions/__init__.py
pybotx/client/exceptions/base.py
pybotx/client/exceptions/callbacks.py
pybotx/client/exceptions/chats.py
pybotx/client/exceptions/common.py
pybotx/client/exceptions/event.py
pybotx/client/exceptions/files.py
pybotx/client/exceptions/http.py
pybotx/client/exceptions/message.py
pybotx-0.75.5.dist-info/METADATA
pybotx-0.75.5.dist-info/WHEEL
pybotx-0.75.5.dist-info/licenses/LICENSE
pybotx-0.75.5.dist-info/RECORD
