Metadata-Version: 2.4
Name: pybotx
Version: 0.75.5
Summary: A python library for interacting with eXpress BotX API
License-File: LICENSE
Author: Sidnev Nikolay
Author-email: nsidnev@ccsteam.ru
Requires-Python: >=3.9,<3.14
Classifier: Programming Language :: Python :: 3
Classifier: Programming Language :: Python :: 3.9
Classifier: Programming Language :: Python :: 3.10
Classifier: Programming Language :: Python :: 3.11
Classifier: Programming Language :: Python :: 3.12
Classifier: Programming Language :: Python :: 3.13
Requires-Dist: aiocsv (>=1.2.3,<=1.4.0)
Requires-Dist: aiofiles (>=0.7.0,<=24.1.0)
Requires-Dist: httpcore (==1.0.9)
Requires-Dist: httpx (>=0.28.0,<0.29.0)
Requires-Dist: loguru (>=0.6.0,<0.7.0)
Requires-Dist: mypy-extensions (>=0.2.0,<=1.1.0)
Requires-Dist: pydantic (>=1.6.0,<1.11.0)
Requires-Dist: pyjwt (>=2.0.0,<3.0.0)
Project-URL: Repository, https://github.com/ExpressApp/pybotx
